reinvent_models/__init__.py
reinvent_models/lib_invent/__init__.py
reinvent_models/lib_invent/enums/__init__.py
reinvent_models/lib_invent/enums/generative_model_parameters.py
reinvent_models/lib_invent/enums/generative_model_regime.py
reinvent_models/lib_invent/models/__init__.py
reinvent_models/lib_invent/models/dataset.py
reinvent_models/lib_invent/models/decorator.py
reinvent_models/lib_invent/models/model.py
reinvent_models/lib_invent/models/vocabulary.py
reinvent_models/link_invent/__init__.py
reinvent_models/link_invent/link_invent_model.py
reinvent_models/link_invent/dataset/__init__.py
reinvent_models/link_invent/dataset/dataset.py
reinvent_models/link_invent/dataset/paired_dataset.py
reinvent_models/link_invent/dto/__init__.py
reinvent_models/link_invent/dto/link_invent_model_parameters_dto.py
reinvent_models/link_invent/dto/sampled_sequence_dto.py
reinvent_models/link_invent/model_vocabulary/__init__.py
reinvent_models/link_invent/model_vocabulary/model_vocabulary.py
reinvent_models/link_invent/model_vocabulary/paired_model_vocabulary.py
reinvent_models/link_invent/model_vocabulary/vocabulary.py
reinvent_models/link_invent/networks/__init__.py
reinvent_models/link_invent/networks/attention_layer.py
reinvent_models/link_invent/networks/decoder.py
reinvent_models/link_invent/networks/encoder.py
reinvent_models/link_invent/networks/encoder_decoder.py
reinvent_models/model_factory/__init__.py
reinvent_models/model_factory/generative_model.py
reinvent_models/model_factory/generative_model_base.py
reinvent_models/model_factory/lib_invent_adapter.py
reinvent_models/model_factory/link_invent_adapter.py
reinvent_models/model_factory/reinvent_core_adapter.py
reinvent_models/model_factory/configurations/__init__.py
reinvent_models/model_factory/configurations/model_configuration.py
reinvent_models/model_factory/enums/__init__.py
reinvent_models/model_factory/enums/model_mode_enum.py
reinvent_models/model_factory/enums/model_parameter_enum.py
reinvent_models-0.0.14.dist-info/METADATA
reinvent_models-0.0.14.dist-info/WHEEL
reinvent_models-0.0.14.dist-info/top_level.txt
reinvent_models-0.0.14.dist-info/RECORD
