Metadata-Version: 2.1
Name: reinvent-models
Version: 0.0.14
Summary: Generative models for Reinvent
Home-page: https://bitbucket.astrazeneca.net/scm/com/reinvent_models.git
Author: MolecularAI
Author-email: patronov@gmail.com
License: UNKNOWN
Platform: UNKNOWN
Classifier: Programming Language :: Python :: 3
Classifier: License :: OSI Approved :: MIT License
Classifier: Operating System :: OS Independent
Requires-Python: >=3.7
